{"code":0,"data":{"current_page":8,"data":[{"appkey":"init","cover":"","cover2":"","duration":6,"file":"https://raw.githubusercontent.com/sjianji/Magic-Cut/main/data/audio/40610022/1024287/33760426.mp3","height":0,"id":"1024287","name":"你别以为有钱了不起","pictureNeed":0,"sort":0,"textNeed":0,"type":"audio","ufid":"33760426","updatetime":"1697698246","version":157,"video":"","videoNeed":0,"width":0},{"appkey":"init","cover":"","cover2":"","duration":3,"file":"https://raw.githubusercontent.com/sjianji/Magic-Cut/main/data/audio/40610022/1024286/85425286.mp3","height":0,"id":"1024286","name":"你别笑","pictureNeed":0,"sort":0,"textNeed":0,"type":"audio","ufid":"85425286","updatetime":"1697698297","version":157,"video":"","videoNeed":0,"width":0},{"appkey":"init","cover":"","cover2":"","duration":18,"file":"https://raw.githubusercontent.com/sjianji/Magic-Cut/main/data/audio/40610022/1024285/79102722.mp3","height":0,"id":"1024285","name":"你happy我不happy","pictureNeed":0,"sort":0,"textNeed":0,"type":"audio","ufid":"79102722","updatetime":"1697698297","version":157,"video":"","videoNeed":0,"width":0},{"appkey":"init","cover":"","cover2":"","duration":8,"file":"https://raw.githubusercontent.com/sjianji/Magic-Cut/main/data/audio/40610022/1024284/18113985.mp3","height":0,"id":"1024284","name":"尼克狐尼克，你被捕了","pictureNeed":0,"sort":0,"textNeed":0,"type":"audio","ufid":"18113985","updatetime":"1697698246","version":157,"video":"","videoNeed":0,"width":0},{"appkey":"init","cover":"","cover2":"","duration":24,"file":"https://raw.githubusercontent.com/sjianji/Magic-Cut/main/data/audio/40610022/1024283/34591278.mp3","height":0,"id":"1024283","name":"男人过了60岁不要穿得太","pictureNeed":0,"sort":0,"textNeed":0,"type":"audio","ufid":"34591278","updatetime":"1697698245","version":157,"video":"","videoNeed":0,"width":0},{"appkey":"init","cover":"","cover2":"","duration":29,"file":"https://raw.githubusercontent.com/sjianji/Magic-Cut/main/data/audio/40610022/1024282/60768924.mp3","height":0,"id":"1024282","name":"男人过了20岁就别再穿得像小孩","pictureNeed":0,"sort":0,"textNeed":0,"type":"audio","ufid":"60768924","updatetime":"1697698245","version":157,"video":"","videoNeed":0,"width":0},{"appkey":"init","cover":"","cover2":"","duration":10,"file":"https://raw.githubusercontent.com/sjianji/Magic-Cut/main/data/audio/40610022/1024281/27957265.mp3","height":0,"id":"1024281","name":"那就倒数3、2、1，茄子","pictureNeed":0,"sort":0,"textNeed":0,"type":"audio","ufid":"27957265","updatetime":"1697698245","version":157,"video":"","videoNeed":0,"width":0},{"appkey":"init","cover":"","cover2":"","duration":34,"file":"https://raw.githubusercontent.com/sjianji/Magic-Cut/main/data/audio/40610022/1024280/40371314.mp3","height":0,"id":"1024280","name":"墨镜嚣张","pictureNeed":0,"sort":0,"textNeed":0,"type":"audio","ufid":"40371314","updatetime":"1697698245","version":157,"video":"","videoNeed":0,"width":0},{"appkey":"init","cover":"","cover2":"","duration":16,"file":"https://raw.githubusercontent.com/sjianji/Magic-Cut/main/data/audio/40610022/1024279/39261403.mp3","height":0,"id":"1024279","name":"魔性螃蟹歌","pictureNeed":0,"sort":0,"textNeed":0,"type":"audio","ufid":"39261403","updatetime":"1697698245","version":157,"video":"","videoNeed":0,"width":0},{"appkey":"init","cover":"","cover2":"","duration":18,"file":"https://raw.githubusercontent.com/sjianji/Magic-Cut/main/data/audio/40610022/1024278/38940055.mp3","height":0,"id":"1024278","name":"魔性斑马-哒哒哒歌","pictureNeed":0,"sort":0,"textNeed":0,"type":"audio","ufid":"38940055","updatetime":"1697698244","version":157,"video":"","videoNeed":0,"width":0},{"appkey":"init","cover":"","cover2":"","duration":13,"file":"https://raw.githubusercontent.com/sjianji/Magic-Cut/main/data/audio/40610022/1024277/69531192.mp3","height":0,"id":"1024277","name":"魔法怎么失灵了","pictureNeed":0,"sort":0,"textNeed":0,"type":"audio","ufid":"69531192","updatetime":"1697698244","version":157,"video":"","videoNeed":0,"width":0},{"appkey":"init","cover":"","cover2":"","duration":11,"file":"https://raw.githubusercontent.com/sjianji/Magic-Cut/main/data/audio/40610022/1024276/55477037.mp3","height":0,"id":"1024276","name":"梦之泪伤，帅气的脸庞","pictureNeed":0,"sort":0,"textNeed":0,"type":"audio","ufid":"55477037","updatetime":"1697698244","version":157,"video":"","videoNeed":0,"width":0},{"appkey":"init","cover":"","cover2":"","duration":29,"file":"https://raw.githubusercontent.com/sjianji/Magic-Cut/main/data/audio/40610022/1024275/28879022.mp3","height":0,"id":"1024275","name":"猛男嘴哥精神氮泵合集","pictureNeed":0,"sort":0,"textNeed":0,"type":"audio","ufid":"28879022","updatetime":"1697698244","version":157,"video":"","videoNeed":0,"width":0},{"appkey":"init","cover":"","cover2":"","duration":15,"file":"https://raw.githubusercontent.com/sjianji/Magic-Cut/main/data/audio/40610022/1024274/80961470.mp3","height":0,"id":"1024274","name":"猛男版 我是广寒宫里的可","pictureNeed":0,"sort":0,"textNeed":0,"type":"audio","ufid":"80961470","updatetime":"1697698243","version":157,"video":"","videoNeed":0,"width":0},{"appkey":"init","cover":"","cover2":"","duration":7,"file":"https://raw.githubusercontent.com/sjianji/Magic-Cut/main/data/audio/40610022/1024273/85064303.mp3","height":0,"id":"1024273","name":"每次都想装作很倔强","pictureNeed":0,"sort":0,"textNeed":0,"type":"audio","ufid":"85064303","updatetime":"1697698243","version":157,"video":"","videoNeed":0,"width":0},{"appkey":"init","cover":"","cover2":"","duration":6,"file":"https://raw.githubusercontent.com/sjianji/Magic-Cut/main/data/audio/40610022/1024272/44402144.mp3","height":0,"id":"1024272","name":"没关系又活了一天已经很","pictureNeed":0,"sort":0,"textNeed":0,"type":"audio","ufid":"44402144","updatetime":"1697698243","version":157,"video":"","videoNeed":0,"width":0},{"appkey":"init","cover":"","cover2":"","duration":23,"file":"https://raw.githubusercontent.com/sjianji/Magic-Cut/main/data/audio/40610022/1024271/80216035.mp3","height":0,"id":"1024271","name":"玫瑰少年-小提琴","pictureNeed":0,"sort":0,"textNeed":0,"type":"audio","ufid":"80216035","updatetime":"1697698243","version":157,"video":"","videoNeed":0,"width":0},{"appkey":"init","cover":"","cover2":"","duration":13,"file":"https://raw.githubusercontent.com/sjianji/Magic-Cut/main/data/audio/40610022/1024270/36810279.mp3","height":0,"id":"1024270","name":"盲人女孩摘下眼罩","pictureNeed":0,"sort":0,"textNeed":0,"type":"audio","ufid":"36810279","updatetime":"1697698243","version":157,"video":"","videoNeed":0,"width":0},{"appkey":"init","cover":"","cover2":"","duration":61,"file":"https://raw.githubusercontent.com/sjianji/Magic-Cut/main/data/audio/40610022/1024269/94426008.mp3","height":0,"id":"1024269","name":"满江红走路bgm","pictureNeed":0,"sort":0,"textNeed":0,"type":"audio","ufid":"94426008","updatetime":"1697698242","version":157,"video":"","videoNeed":0,"width":0},{"appkey":"init","cover":"","cover2":"","duration":15,"file":"https://raw.githubusercontent.com/sjianji/Magic-Cut/main/data/audio/40610022/1024268/37286644.mp3","height":0,"id":"1024268","name":"麦当劳之歌","pictureNeed":0,"sort":0,"textNeed":0,"type":"audio","ufid":"37286644","updatetime":"1697698242","version":157,"video":"","videoNeed":0,"width":0}],"last_page":15,"per_page":20,"total":283},"msg":"success"}