{"code":0,"msg":"success","data":[{"id":"14871637","utid":"14871637","name":"Landscape","name_en":"","appkey":"init","icon":"","icon_checked":"","icon_unchecked":"","type":"templateapi_theme","updatetime":"2023-08-02 13:26:06","classify":"category","version":0,"sort":0,"sync":"2023-08-02 13:26:06","extra":{},"polyglot":{"en":"Landscape"},"status":1},{"id":"59417489","utid":"59417489","name":"Portrait","name_en":"","appkey":"init","icon":"","icon_checked":"","icon_unchecked":"","type":"templateapi_theme","updatetime":"2023-08-02 13:25:49","classify":"category","version":0,"sort":0,"sync":"2023-08-02 13:25:49","extra":{},"polyglot":{"en":"Portrait"},"status":1}]}