{"code":0,"data":[{"appkey":"init","cover":"https://raw.githubusercontent.com/chuyonglong/migic-video/main/Transtins/69916171/1022412/cover.gif","cover2":"","duration":0,"file":"https://raw.githubusercontent.com/chuyonglong/migic-video/main/Transtins/69916171/1022412/file.zip","height":0,"id":"1022412","name":"Clouds","pictureNeed":0,"sort":1,"textNeed":0,"type":"transition","ufid":"80289829","updatetime":"1698815677","version":157,"video":"","videoNeed":0,"width":0},{"appkey":"init","cover":"https://raw.githubusercontent.com/chuyonglong/migic-video/main/Transtins/69916171/1022413/cover.gif","cover2":"","duration":0,"file":"https://raw.githubusercontent.com/chuyonglong/migic-video/main/Transtins/69916171/1022413/file.zip","height":0,"id":"1022413","name":"Clouds II","pictureNeed":0,"sort":2,"textNeed":0,"type":"transition","ufid":"63876078","updatetime":"1698815677","version":157,"video":"","videoNeed":0,"width":0},{"appkey":"init","cover":"https://raw.githubusercontent.com/chuyonglong/migic-video/main/Transtins/69916171/1022411/cover.gif","cover2":"","duration":0,"file":"https://raw.githubusercontent.com/chuyonglong/migic-video/main/Transtins/69916171/1022411/file.zip","height":0,"id":"1022411","name":"Traces of time","pictureNeed":0,"sort":3,"textNeed":0,"type":"transition","ufid":"87528957","updatetime":"1698815677","version":157,"video":"","videoNeed":0,"width":0},{"appkey":"init","cover":"https://raw.githubusercontent.com/chuyonglong/migic-video/main/Transtins/69916171/1022410/cover.gif","cover2":"","duration":0,"file":"https://raw.githubusercontent.com/chuyonglong/migic-video/main/Transtins/69916171/1022410/file.zip","height":0,"id":"1022410","name":"Torn paper","pictureNeed":0,"sort":4,"textNeed":0,"type":"transition","ufid":"85025595","updatetime":"1698815677","version":157,"video":"","videoNeed":0,"width":0},{"appkey":"init","cover":"https://raw.githubusercontent.com/chuyonglong/migic-video/main/Transtins/69916171/1022409/cover.gif","cover2":"","duration":0,"file":"https://raw.githubusercontent.com/chuyonglong/migic-video/main/Transtins/69916171/1022409/file.zip","height":0,"id":"1022409","name":"Ink wash","pictureNeed":0,"sort":5,"textNeed":0,"type":"transition","ufid":"28904864","updatetime":"1698815677","version":157,"video":"","videoNeed":0,"width":0},{"appkey":"init","cover":"https://raw.githubusercontent.com/chuyonglong/migic-video/main/Transtins/69916171/1022407/cover.gif","cover2":"","duration":0,"file":"https://raw.githubusercontent.com/chuyonglong/migic-video/main/Transtins/69916171/1022407/file.zip","height":0,"id":"1022407","name":"Color dissolve II","pictureNeed":0,"sort":6,"textNeed":0,"type":"transition","ufid":"44114991","updatetime":"1698815677","version":157,"video":"","videoNeed":0,"width":0},{"appkey":"init","cover":"https://raw.githubusercontent.com/chuyonglong/migic-video/main/Transtins/69916171/1022408/cover.gif","cover2":"","duration":0,"file":"https://raw.githubusercontent.com/chuyonglong/migic-video/main/Transtins/69916171/1022408/file.zip","height":0,"id":"1022408","name":"Color dissolve III","pictureNeed":0,"sort":7,"textNeed":0,"type":"transition","ufid":"96596289","updatetime":"1698815677","version":157,"video":"","videoNeed":0,"width":0},{"appkey":"init","cover":"https://raw.githubusercontent.com/chuyonglong/migic-video/main/Transtins/69916171/1022405/cover.gif","cover2":"","duration":0,"file":"https://raw.githubusercontent.com/chuyonglong/migic-video/main/Transtins/69916171/1022405/file.zip","height":0,"id":"1022405","name":"Gradient erasure","pictureNeed":0,"sort":8,"textNeed":0,"type":"transition","ufid":"66960045","updatetime":"1698815677","version":157,"video":"","videoNeed":0,"width":0},{"appkey":"init","cover":"https://raw.githubusercontent.com/chuyonglong/migic-video/main/Transtins/69916171/1022404/cover.gif","cover2":"","duration":0,"file":"https://raw.githubusercontent.com/chuyonglong/migic-video/main/Transtins/69916171/1022404/file.zip","height":0,"id":"1022404","name":"Brush erasure","pictureNeed":0,"sort":9,"textNeed":0,"type":"transition","ufid":"86832033","updatetime":"1698815677","version":157,"video":"","videoNeed":0,"width":0},{"appkey":"init","cover":"https://raw.githubusercontent.com/chuyonglong/migic-video/main/Transtins/69916171/1022402/cover.gif","cover2":"","duration":0,"file":"https://raw.githubusercontent.com/chuyonglong/migic-video/main/Transtins/69916171/1022402/file.zip","height":0,"id":"1022402","name":"Overlay","pictureNeed":0,"sort":10,"textNeed":0,"type":"transition","ufid":"74416093","updatetime":"1698815677","version":157,"video":"","videoNeed":0,"width":0},{"appkey":"init","cover":"https://raw.githubusercontent.com/chuyonglong/migic-video/main/Transtins/69916171/1022401/cover.gif","cover2":"","duration":0,"file":"https://raw.githubusercontent.com/chuyonglong/migic-video/main/Transtins/69916171/1022401/file.zip","height":0,"id":"1022401","name":"Layer blend","pictureNeed":0,"sort":11,"textNeed":0,"type":"transition","ufid":"98864609","updatetime":"1698815677","version":157,"video":"","videoNeed":0,"width":0}],"msg":"success"}
