{"code":0,"msg":"success","data":[{"id":"1020657","ufid":"16685996","name":"Shining 1","file":"http:\/\/rdfile.oss-cn-hangzhou.aliyuncs.com\/filemanage\/init\/filter2\/1677641857635\/file_init.zip?nonce=cfcd208495d565ef66e7dff9f98764da","cover":"http:\/\/rdfile.oss-cn-hangzhou.aliyuncs.com\/filemanage\/init\/filter2\/1677641857635\/cover_init.gif?nonce=cfcd208495d565ef66e7dff9f98764da","updatetime":"0","height":200,"width":200,"video":"","sort":100,"version":161,"cover2":"","appkey":"init","duration":0,"extra":{},"polyglot":{"en":"Shining 1"},"category":"0","audit":0,"is_ugc":0,"type":"filter2"}]}